tgedr/__init__.py
tgedr/simplepipe/etl/etl.py
tgedr/simplepipe/etl/news_etl.py
tgedr/simplepipe/etl/sentiment_etl.py
tgedr/simplepipe/news/article.py
tgedr/simplepipe/news/fetcher.py
tgedr/simplepipe/news/finnhub_fetcher.py
tgedr/simplepipe/store/parquet_store.py
tgedr/simplepipe/store/store.py
tgedr/simplepipe/utils/entrypoint.py
tgedr/simplepipe/utils/validation/data_validation.py
tgedr/simplepipe/utils/validation/pandas_validation.py
tgedr_simplepipe-0.0.11.dist-info/METADATA
tgedr_simplepipe-0.0.11.dist-info/WHEEL
tgedr_simplepipe-0.0.11.dist-info/entry_points.txt
tgedr_simplepipe-0.0.11.dist-info/top_level.txt
tgedr_simplepipe-0.0.11.dist-info/RECORD
