Metadata-Version: 2.4
Name: tgedr-simplepipe
Version: 0.0.11
Summary: this is an example of a simple data pipeline
Author-email: tiago <jtviegas@gmail.com>
Requires-Python: >=3.12
Requires-Dist: pandas>=2.3.0
Requires-Dist: finnhub-python>=2.4.26
Requires-Dist: pyarrow>=23.0.0
Requires-Dist: transformers>=4.57.6
Requires-Dist: torch>=2.10.0
Requires-Dist: great-expectations~=0.18.8
